latch_persistence/__init__.py
latch_persistence/py.typed
latch_persistence-0.1.5.dist-info/METADATA
latch_persistence-0.1.5.dist-info/WHEEL
latch_persistence-0.1.5.dist-info/licenses/LICENSE
latch_persistence-0.1.5.dist-info/RECORD
