Metadata-Version: 2.4
Name: latch_persistence
Version: 0.1.5
Summary: Add your description here
Author-email: Ayush Kamat <ayush@latch.bio>
License: Creative Commons Legal Code
License-File: LICENSE
Requires-Python: >=3.9
Requires-Dist: requests>=2.32.3
